{
  "provinces": {
    "福建": {
      "name": "福建",
      "title": "古桥之乡",
      "subtitle": "海上丝绸之路的桥梁明珠",
      "count": 42,
      "history": "福建地处东南沿海，水系发达，自古便是海上丝绸之路的重要起点。宋代以来，福建桥梁建造技术达到鼎盛，以石梁桥最为著名。泉州港的繁荣催生了大量跨海石桥的建造，形成了独特的'闽南桥梁文化'。",
      "features": [
        "跨海石梁桥技术领先全国",
        "筏型基础与养蛎固基法独创",
        "桥上建亭、桥边建塔的风气盛行",
        "石雕艺术与桥梁建筑完美结合"
      ],
      "representatives": [
        {
          "name": "洛阳桥",
          "dynasty": "宋",
          "span": "834米",
          "description": "中国第一座跨海石梁桥，蔡襄主持建造，首创筏型基础和养蛎固基法"
        },
        {
          "name": "安平桥",
          "dynasty": "宋",
          "span": "2255米",
          "description": "天下无桥长此桥，中国古代最长的石梁桥"
        },
        {
          "name": "江东桥",
          "dynasty": "宋",
          "span": "285米",
          "description": "世界最大石梁桥，单块石梁重达200余吨"
        }
      ],
      "stories": [
        {
          "title": "蔡襄造洛阳桥",
          "content": "北宋皇祐年间，泉州太守蔡襄主持建造洛阳桥。面对洛阳江入海口的急流，蔡襄首创筏型基础，并在桥基上养殖牡蛎，利用牡蛎壳的附着作用加固桥基，这就是著名的'养蛎固基法'。此法后来被广泛应用于沿海桥梁建造。"
        },
        {
          "title": "安平桥的传说",
          "content": "相传安平桥建造时，工匠们日夜施工，感动了海神。海神便让潮水退去三天，让工匠们得以顺利铺设石梁。从此，安平桥历经八百年风雨，依然屹立不倒。"
        }
      ],
      "culture": "福建古桥不仅是交通设施，更是海上丝绸之路繁荣的见证。桥梁上的石雕、碑刻记录了宋元时期泉州港的辉煌历史，是研究中国古代海外贸易和桥梁技术的重要实物资料。",
      "mainDynasty": "宋",
      "mainType": "梁桥",
      "climate": "亚热带海洋性季风气候，雨量充沛，水系发达"
    },
    "浙江": {
      "name": "浙江",
      "title": "江南水乡桥韵",
      "subtitle": "烟雨江南的诗意桥梁",
      "count": 38,
      "history": "浙江自古为江南水乡核心区域，河网密布，桥梁众多。从吴越国到南宋，浙江桥梁建造技艺不断精进。廊桥、拱桥、梁桥各具特色，形成了独特的江南桥梁文化。绍兴一地便有古桥数百座，被誉为'桥乡'。",
      "features": [
        "廊桥建筑艺术精湛",
        "石拱桥技术成熟",
        "桥乡文化底蕴深厚",
        "园林桥梁独具匠心"
      ],
      "representatives": [
        {
          "name": "八字桥",
          "dynasty": "宋",
          "span": "4.5米",
          "description": "中国现存最古老的城市桥梁，形如八字，巧夺天工"
        },
        {
          "name": "广济桥",
          "dynasty": "明",
          "span": "517米",
          "description": "世界上最早的启闭式桥梁，集梁桥、拱桥、浮桥于一体"
        },
        {
          "name": "通济桥",
          "dynasty": "元",
          "span": "43.8米",
          "description": "浙东第一桥，姚江上最大的三孔石拱桥"
        }
      ],
      "stories": [
        {
          "title": "八字桥的智慧",
          "content": "绍兴八字桥建于南宋嘉泰年间，因其形如'八'字而得名。桥的设计极为巧妙，一桥跨三河，连接三街，解决了复杂的水陆交通问题，被誉为古代城市桥梁设计的典范。"
        },
        {
          "title": "广济桥的启闭之谜",
          "content": "潮州广济桥中段由十八只梭船组成浮桥，可开可合。白天连接两岸，夜晚解开浮桥，让大型船只通过。这种启闭式设计在世界桥梁史上独一无二，体现了古人的智慧。"
        }
      ],
      "culture": "浙江古桥承载着江南水乡的诗意与浪漫。白墙黑瓦间，小桥流水人家，构成了独特的江南画卷。桥梁不仅是交通要道，更是文人墨客吟咏的对象，留下了无数诗词佳作。",
      "mainDynasty": "宋",
      "mainType": "拱桥",
      "climate": "亚热带季风气候，四季分明，水网密布"
    },
    "江苏": {
      "name": "江苏",
      "title": "运河桥韵",
      "subtitle": "大运河上的桥梁明珠",
      "count": 35,
      "history": "江苏地处京杭大运河中段，自古便是南北交通要道。运河的开通催生了大量桥梁的建造，从苏州的园林小桥到扬州的运河大桥，各具特色。明清时期，江苏桥梁建造达到鼎盛，形成了独特的运河桥梁文化。",
      "features": [
        "运河桥梁规模宏大",
        "园林桥梁精致典雅",
        "石拱技术炉火纯青",
        "桥梁与城市融为一体"
      ],
      "representatives": [
        {
          "name": "宝带桥",
          "dynasty": "唐",
          "span": "317米",
          "description": "中国现存最长、保存最完整的多孔石拱桥，有53孔"
        },
        {
          "name": "枫桥",
          "dynasty": "唐",
          "span": "39.6米",
          "description": "因张继《枫桥夜泊》而闻名天下，文化名桥"
        },
        {
          "name": "五亭桥",
          "dynasty": "清",
          "span": "55.3米",
          "description": "中国最美的桥，扬州瘦西湖的标志性建筑"
        }
      ],
      "stories": [
        {
          "title": "宝带桥的由来",
          "content": "唐元和年间，苏州刺史王仲舒捐出宝带资助建桥，故名宝带桥。此桥横跨澹台湖，是古代苏州通往杭州的必经之路。桥身如一条玉带横卧湖面，美不胜收。"
        },
        {
          "title": "枫桥夜泊",
          "content": "唐代诗人张继途经苏州，夜泊枫桥，听寒山寺钟声，写下千古名篇《枫桥夜泊》：'月落乌啼霜满天，江枫渔火对愁眠。姑苏城外寒山寺，夜半钟声到客船。'从此枫桥名扬天下。"
        }
      ],
      "culture": "江苏古桥与运河文化、园林文化紧密相连。桥梁不仅是交通设施，更是城市景观的重要组成部分。苏州园林中的小桥流水，扬州瘦西湖的五亭桥，都是中国桥梁艺术的瑰宝。",
      "mainDynasty": "明",
      "mainType": "拱桥",
      "climate": "亚热带季风气候，四季分明，水网密布"
    },
    "河北": {
      "name": "河北",
      "title": "北方古桥典范",
      "subtitle": "赵州桥的故乡",
      "count": 18,
      "history": "河北地处华北平原，是古代中原通往北方的重要通道。隋代李春设计的赵州桥开创了敞肩拱桥的先河，成为世界桥梁史上的里程碑。河北古桥以雄伟壮观、结构科学著称，代表了北方桥梁建造的最高水平。",
      "features": [
        "敞肩拱技术世界首创",
        "桥梁结构科学合理",
        "北方风格雄伟壮观",
        "工程技术领先世界"
      ],
      "representatives": [
        {
          "name": "赵州桥",
          "dynasty": "隋",
          "span": "37.02米",
          "description": "世界现存最早、保存最完好的敞肩石拱桥，被誉为'天下第一桥'"
        },
        {
          "name": "永通桥",
          "dynasty": "唐",
          "span": "25.5米",
          "description": "赵州桥的姊妹桥，结构相似，规模略小"
        }
      ],
      "stories": [
        {
          "title": "鲁班造桥的传说",
          "content": "相传赵州桥是鲁班所建。鲁班一夜之间造好大桥，张果老骑着毛驴来试探桥的坚固。毛驴背上驮着日月星辰，桥身微微晃动，鲁班跳入水中托住桥身，桥才稳固。至今桥上还留有张果老驴蹄印和鲁班手印。"
        },
        {
          "title": "李春的智慧",
          "content": "赵州桥的设计者李春是隋代杰出的工匠。他首创敞肩拱结构，在大拱两肩各开两个小拱，既减轻桥身重量，又增加泄洪能力。这种设计比欧洲早了800多年，是世界桥梁史上的伟大创举。"
        }
      ],
      "culture": "赵州桥不仅是一座桥梁，更是中国古代科技的象征。它的建造技术领先世界近千年，体现了中华民族的智慧和创造力。赵州桥的存在，证明了中国古代桥梁技术在世界上的领先地位。",
      "mainDynasty": "隋",
      "mainType": "拱桥",
      "climate": "温带季风气候，四季分明，降水集中"
    },
    "广东": {
      "name": "广东",
      "title": "岭南桥韵",
      "subtitle": "海上丝绸之路的桥梁见证",
      "count": 22,
      "history": "广东地处岭南，自古是海上丝绸之路的重要起点。珠江三角洲水网密布，桥梁建造历史悠久。广济桥作为世界上最早的启闭式桥梁，代表了中国桥梁技术的最高成就。岭南古桥融合了中原文化与海洋文化，形成了独特的风格。",
      "features": [
        "启闭式桥梁世界首创",
        "岭南风格独特鲜明",
        "海洋文化影响深远",
        "桥梁装饰精美华丽"
      ],
      "representatives": [
        {
          "name": "广济桥",
          "dynasty": "明",
          "span": "517米",
          "description": "世界上最早的启闭式桥梁，集梁桥、拱桥、浮桥于一体"
        },
        {
          "name": "风雨桥",
          "dynasty": "清",
          "span": "76米",
          "description": "岭南地区典型的廊桥，桥上建亭，可供行人避雨休憩"
        }
      ],
      "stories": [
        {
          "title": "广济桥的梭船",
          "content": "广济桥中段由十八只梭船组成浮桥，可开可合。白天梭船相连，供行人通过；夜晚解开浮桥，让大型船只通行。这种启闭式设计在世界桥梁史上独一无二，体现了潮州人民的智慧。"
        },
        {
          "title": "韩愈与广济桥",
          "content": "唐代大文豪韩愈被贬潮州期间，关心民生，倡导建桥。后人为了纪念他，将广济桥又称'湘子桥'，传说韩愈的侄孙韩湘子也参与了建桥。"
        }
      ],
      "culture": "广东古桥是岭南文化的重要组成部分，见证了海上丝绸之路的繁荣。桥梁上的石雕、木雕精美绝伦，反映了岭南人民的审美情趣和工艺水平。",
      "mainDynasty": "明",
      "mainType": "梁桥",
      "climate": "亚热带季风气候，高温多雨，台风频繁"
    },
    "四川": {
      "name": "四川",
      "title": "蜀道桥韵",
      "subtitle": "天府之国的桥梁奇观",
      "count": 25,
      "history": "四川盆地水系发达，岷江、沱江、嘉陵江等大河纵横。古蜀先民因地制宜，创造了索桥、廊桥、拱桥等多种桥梁形式。泸定桥作为世界著名的铁索桥，见证了中国革命的历史。四川古桥融合了汉族与少数民族文化，风格独特。",
      "features": [
        "铁索桥技术精湛",
        "廊桥建筑规模宏大",
        "多民族风格融合",
        "革命历史意义深远"
      ],
      "representatives": [
        {
          "name": "泸定桥",
          "dynasty": "清",
          "span": "103米",
          "description": "世界著名的铁索桥，红军长征'飞夺泸定桥'发生地"
        },
        {
          "name": "安澜桥",
          "dynasty": "清",
          "span": "280米",
          "description": "中国古代最长的竹索桥，横跨岷江"
        }
      ],
      "stories": [
        {
          "title": "飞夺泸定桥",
          "content": "1935年5月29日，中国工农红军长征途中，22名勇士冒着敌人的枪林弹雨，攀着悬空的铁索，冲向对岸，成功夺取泸定桥。这一壮举成为中国革命史上的传奇，泸定桥也因此名扬天下。"
        },
        {
          "title": "安澜桥的传说",
          "content": "相传安澜桥是一位名叫何先德的工匠所建。他为了建造这座横跨岷江的竹索桥，呕心沥血，最终成功。桥建成后，当地百姓过江不再需要渡船，安全便利，故名'安澜'。"
        }
      ],
      "culture": "四川古桥是巴蜀文化的重要载体，见证了蜀道的艰险与人民的智慧。从古代的竹索桥到现代的铁索桥，四川桥梁技术的发展历程是中国桥梁史的重要组成部分。",
      "mainDynasty": "清",
      "mainType": "索桥",
      "climate": "亚热带季风气候，盆地地形，雨量充沛"
    },
    "云南": {
      "name": "云南",
      "title": "滇云桥韵",
      "subtitle": "多民族的桥梁艺术",
      "count": 20,
      "history": "云南地处西南边陲，山川纵横，河流湍急。各民族因地制宜，创造了丰富多彩的桥梁形式。傣族的竹桥、彝族的藤桥、纳西族的石拱桥，各具特色。双龙桥作为云南最大的古石拱桥，是汉族与少数民族文化融合的典范。",
      "features": [
        "多民族桥梁风格各异",
        "藤桥、竹桥独具特色",
        "石拱桥规模宏大",
        "桥梁与自然和谐统一"
      ],
      "representatives": [
        {
          "name": "双龙桥",
          "dynasty": "清",
          "span": "148米",
          "description": "云南最大的古石拱桥，十七孔连拱，气势恢宏"
        },
        {
          "name": "霁虹桥",
          "dynasty": "明",
          "span": "106米",
          "description": "世界最古老的铁索桥，横跨澜沧江"
        }
      ],
      "stories": [
        {
          "title": "双龙桥的传说",
          "content": "相传建桥时，有两条神龙在河中戏水，阻挡施工。工匠们设坛祭祀，神龙化作两座小山，分别位于桥的两端。桥建成后，便以'双龙'命名，寓意吉祥。"
        },
        {
          "title": "霁虹桥的险峻",
          "content": "霁虹桥横跨澜沧江，两岸悬崖峭壁，江水湍急。古人形容此处'水如奔马，声若雷鸣'。在这样的险要之地建造铁索桥，难度可想而知。霁虹桥的存在，是古代桥梁技术的奇迹。"
        }
      ],
      "culture": "云南古桥是多民族文化的结晶，反映了各民族的智慧和审美情趣。桥梁不仅是交通设施，更是民族团结和文化交流的象征。",
      "mainDynasty": "清",
      "mainType": "拱桥",
      "climate": "亚热带高原季风气候，气候多样"
    },
    "贵州": {
      "name": "贵州",
      "title": "黔山桥韵",
      "subtitle": "喀斯特地貌上的桥梁奇观",
      "count": 15,
      "history": "贵州地处云贵高原，喀斯特地貌发育，山高谷深，河流湍急。苗族、侗族等少数民族创造了独特的风雨桥，桥上建廊，廊上建亭，可供行人避雨休憩，是侗族建筑艺术的代表。贵州古桥融合了自然景观与人文建筑，形成了独特的桥梁文化。",
      "features": [
        "风雨桥建筑艺术精湛",
        "侗族木构技术高超",
        "桥梁与山水融为一体",
        "民族文化特色鲜明"
      ],
      "representatives": [
        {
          "name": "地坪风雨桥",
          "dynasty": "清",
          "span": "56米",
          "description": "全国重点文物保护单位，侗族风雨桥的代表作"
        },
        {
          "name": "葛镜桥",
          "dynasty": "明",
          "span": "52米",
          "description": "贵州最大的石拱桥，横跨麻哈江"
        }
      ],
      "stories": [
        {
          "title": "风雨桥的由来",
          "content": "侗族风雨桥又称'花桥'，是侗族村寨的标志性建筑。桥上建廊，廊上建亭，可供行人避雨休憩。风雨桥不仅是交通设施，更是侗族人民社交、娱乐的场所，体现了侗族'以人为本'的建筑理念。"
        },
        {
          "title": "葛镜造桥",
          "content": "明代贵州人葛镜立志在麻哈江上建桥，方便两岸百姓。他倾尽家财，历时三十年，终于建成葛镜桥。后人为了纪念他，在桥头立碑，颂扬他的功德。"
        }
      ],
      "culture": "贵州古桥是侗族、苗族等少数民族文化的载体，反映了各民族的建筑智慧和审美情趣。风雨桥不仅是交通设施，更是民族团结和文化传承的象征。",
      "mainDynasty": "清",
      "mainType": "廊桥",
      "climate": "亚热带季风气候，喀斯特地貌发育"
    },
    "北京": {
      "name": "北京",
      "title": "京华桥韵",
      "subtitle": "皇家园林中的桥梁艺术",
      "count": 12,
      "history": "北京作为元、明、清三朝都城，皇家园林中的桥梁建造达到了极高的艺术水平。颐和园的十七孔桥、北海公园的永安桥，都是中国园林桥梁的杰作。北京古桥融合了皇家气派与园林艺术，体现了中国传统建筑的精髓。",
      "features": [
        "皇家园林桥梁精美",
        "汉白玉石雕工艺精湛",
        "桥梁与园林融为一体",
        "皇家气派庄重大气"
      ],
      "representatives": [
        {
          "name": "十七孔桥",
          "dynasty": "清",
          "span": "150米",
          "description": "颐和园标志性建筑，十七孔连拱，如长虹卧波"
        },
        {
          "name": "卢沟桥",
          "dynasty": "金",
          "span": "266.5米",
          "description": "中国四大古桥之一，卢沟桥事变发生地"
        }
      ],
      "stories": [
        {
          "title": "十七孔桥的狮子",
          "content": "十七孔桥上雕刻有544只石狮子，大小不一，形态各异。据说没有两只狮子是完全相同的。这些石狮子是中国石雕艺术的瑰宝，展现了清代工匠的高超技艺。"
        },
        {
          "title": "卢沟桥事变",
          "content": "1937年7月7日，日军在卢沟桥附近进行军事演习，借口士兵失踪，向中国军队发起进攻，史称'卢沟桥事变'或'七七事变'。这一事件标志着中国抗日战争全面爆发，卢沟桥因此成为中华民族抗战的历史见证。"
        }
      ],
      "culture": "北京古桥承载着深厚的历史文化内涵。从皇家园林的精美桥梁到卢沟桥的历史见证，北京古桥是中国历史文化的缩影。",
      "mainDynasty": "清",
      "mainType": "拱桥",
      "climate": "温带季风气候，四季分明"
    },
    "山西": {
      "name": "山西",
      "title": "晋商桥韵",
      "subtitle": "晋商故里的桥梁遗存",
      "count": 14,
      "history": "山西地处黄土高原，是中华文明的重要发祥地。晋商的崛起带动了桥梁建造的繁荣，许多古桥至今保存完好。山西古桥以石拱桥为主，结构坚固，造型古朴，体现了北方桥梁的典型特征。",
      "features": [
        "石拱桥结构坚固",
        "晋商文化影响深远",
        "桥梁造型古朴大方",
        "历史遗存保存完好"
      ],
      "representatives": [
        {
          "name": "晋祠鱼沼飞梁",
          "dynasty": "宋",
          "span": "18米",
          "description": "中国现存唯一的十字形古桥，造型独特"
        },
        {
          "name": "普济桥",
          "dynasty": "金",
          "span": "60米",
          "description": "山西保存最完好的金代石拱桥"
        }
      ],
      "stories": [
        {
          "title": "鱼沼飞梁",
          "content": "晋祠鱼沼飞梁建于北宋，是中国现存唯一的十字形古桥。桥下为方形鱼沼，桥上为十字形飞梁，造型独特，结构精巧。古人形容其'架虚为桥，若飞也'，故名'飞梁'。"
        }
      ],
      "culture": "山西古桥是晋商文化的重要组成部分，见证了晋商的辉煌历史。桥梁上的碑刻、题记记录了晋商捐资建桥的善举，反映了晋商'义利并举'的商业伦理。",
      "mainDynasty": "宋",
      "mainType": "拱桥",
      "climate": "温带大陆性季风气候，四季分明"
    },
    "广西": {
      "name": "广西",
      "title": "壮乡桥韵",
      "subtitle": "风雨桥的故乡",
      "count": 18,
      "history": "广西地处岭南，山清水秀，是壮族、侗族等少数民族聚居地。侗族风雨桥是广西最具特色的桥梁形式，桥上建廊，廊上建亭，可供行人避雨休憩。程阳永济桥作为侗族风雨桥的代表作，是世界建筑史上的奇迹。",
      "features": [
        "风雨桥建筑艺术精湛",
        "侗族木构技术高超",
        "桥梁与村寨融为一体",
        "民族文化特色鲜明"
      ],
      "representatives": [
        {
          "name": "程阳永济桥",
          "dynasty": "民国",
          "span": "77.76米",
          "description": "世界四大历史名桥之一，侗族风雨桥的杰出代表"
        },
        {
          "name": "三江风雨桥",
          "dynasty": "清",
          "span": "368米",
          "description": "世界最长风雨桥，集桥、廊、亭于一体"
        }
      ],
      "stories": [
        {
          "title": "程阳永济桥的建造",
          "content": "程阳永济桥建于1912年，由当地侗族工匠设计建造。整座桥不用一钉一铆，全靠榫卯结构连接，展现了侗族人民高超的建筑技艺。桥上建有三座塔亭，飞檐翘角，气势恢宏。"
        }
      ],
      "culture": "广西风雨桥是侗族文化的象征，体现了侗族人民'以人为本'的建筑理念。风雨桥不仅是交通设施，更是村民议事、社交、娱乐的公共场所。",
      "mainDynasty": "清",
      "mainType": "风雨桥",
      "climate": "亚热带季风气候，雨量充沛"
    },
    "湖南": {
      "name": "湖南",
      "title": "潇湘桥韵",
      "subtitle": "湘西风雨桥之乡",
      "count": 15,
      "history": "湖南地处洞庭湖之南，湘江贯穿全境。湘西地区是苗族、土家族聚居地，风雨桥建筑独具特色。凤凰虹桥横跨沱江，是湘西最著名的古桥之一。湖南古桥融合了汉族与少数民族文化，风格独特。",
      "features": [
        "风雨桥建筑精美",
        "湘西民族风格浓郁",
        "桥梁与古镇相映成趣",
        "历史文化底蕴深厚"
      ],
      "representatives": [
        {
          "name": "凤凰虹桥",
          "dynasty": "清",
          "span": "112米",
          "description": "湘西凤凰古城标志性建筑，横跨沱江"
        },
        {
          "name": "龙津风雨桥",
          "dynasty": "明",
          "span": "246.7米",
          "description": "世界最大风雨桥，侗族建筑艺术的杰作"
        }
      ],
      "stories": [
        {
          "title": "凤凰虹桥的传说",
          "content": "相传凤凰虹桥由当地苗族首领设计建造。桥建成后，常有凤凰在桥上栖息，故名'虹桥'。如今，虹桥已成为凤凰古城的标志性建筑，吸引着无数游客前来观赏。"
        }
      ],
      "culture": "湖南古桥是湘西文化的重要组成部分，见证了苗族、土家族等少数民族的历史变迁。桥梁上的雕刻、彩绘反映了各民族的审美情趣和文化传统。",
      "mainDynasty": "清",
      "mainType": "风雨桥",
      "climate": "亚热带季风气候，四季分明"
    },
    "上海": {
      "name": "上海",
      "title": "沪上桥韵",
      "subtitle": "江南水乡的桥梁遗存",
      "count": 6,
      "history": "上海地处长江入海口，河网密布，自古便是江南水乡的一部分。青浦、松江等地保存着众多古桥，见证了上海从渔村到国际大都市的变迁。放生桥是上海地区最著名的古桥，横跨漕港河，气势恢宏。",
      "features": [
        "江南水乡桥梁风格",
        "石拱桥技术精湛",
        "古镇桥梁保存完好",
        "历史文化底蕴深厚"
      ],
      "representatives": [
        {
          "name": "放生桥",
          "dynasty": "明",
          "span": "70.8米",
          "description": "上海最大石拱桥，朱家角古镇标志性建筑"
        },
        {
          "name": "普济桥",
          "dynasty": "元",
          "span": "26.7米",
          "description": "上海最古老的石拱桥，青浦区文物保护单位"
        }
      ],
      "stories": [
        {
          "title": "放生桥的由来",
          "content": "放生桥建于明代，因桥下常有僧人放生而得名。桥为五孔石拱桥，横跨漕港河，是朱家角古镇的标志性建筑。每逢节日，桥上人流如织，热闹非凡。"
        }
      ],
      "culture": "上海古桥是江南水乡文化的遗存，见证了上海的历史变迁。从古老的石拱桥到现代的跨海大桥，上海桥梁的发展史是中国桥梁史的缩影。",
      "mainDynasty": "明",
      "mainType": "拱桥",
      "climate": "亚热带季风气候，四季分明"
    },
    "江西": {
      "name": "江西",
      "title": "赣鄱桥韵",
      "subtitle": "赣江上的桥梁明珠",
      "count": 5,
      "history": "江西地处赣江流域，鄱阳湖平原水网密布。赣州古浮桥是江西最具特色的古桥，由百余只木船连接而成，横跨贡江，是古代浮桥技术的活化石。江西古桥以实用为主，体现了赣地人民的务实精神。",
      "features": [
        "浮桥技术独特",
        "桥梁实用性强",
        "赣江水系桥梁众多",
        "历史文化价值突出"
      ],
      "representatives": [
        {
          "name": "赣州古浮桥",
          "dynasty": "宋",
          "span": "400米",
          "description": "中国现存最古老的浮桥，由百余只木船连接而成"
        },
        {
          "name": "文昌桥",
          "dynasty": "明",
          "span": "240米",
          "description": "抚州标志性古桥，横跨抚河"
        }
      ],
      "stories": [
        {
          "title": "赣州古浮桥",
          "content": "赣州古浮桥始建于宋代，由百余只木船用铁链连接而成。每天定时开启，让船只通行。这座浮桥历经八百余年风雨，至今仍在使用，是中国浮桥技术的活化石。"
        }
      ],
      "culture": "江西古桥是赣文化的载体，见证了赣江流域的历史变迁。赣州古浮桥作为世界上现存最古老的浮桥，是中国桥梁史上的珍贵遗产。",
      "mainDynasty": "宋",
      "mainType": "浮桥",
      "climate": "亚热带季风气候，雨量充沛"
    },
    "陕西": {
      "name": "陕西",
      "title": "秦川桥韵",
      "subtitle": "丝绸之路的桥梁遗存",
      "count": 4,
      "history": "陕西是中华文明的重要发祥地，古都长安是丝绸之路的起点。灞桥作为古代长安的东部门户，见证了无数离别与重逢。陕西古桥以石拱桥为主，历史悠久，文化底蕴深厚。",
      "features": [
        "历史悠久的石拱桥",
        "丝绸之路文化影响",
        "古都桥梁遗存丰富",
        "文化价值突出"
      ],
      "representatives": [
        {
          "name": "灞桥",
          "dynasty": "汉",
          "span": "400米",
          "description": "古代长安东部门户，'灞桥折柳'典故出处"
        },
        {
          "name": "渭水桥",
          "dynasty": "唐",
          "span": "300米",
          "description": "唐代长安通往西域的重要桥梁"
        }
      ],
      "stories": [
        {
          "title": "灞桥折柳",
          "content": "古人送别亲友，常在灞桥折柳相赠，以表惜别之情。'灞桥折柳'因此成为中国文化中送别的经典意象，留下了无数诗词佳作。李白诗云：'箫声咽，秦娥梦断秦楼月。秦楼月，年年柳色，灞陵伤别。'"
        }
      ],
      "culture": "陕西古桥是丝路文化的重要组成部分，见证了长安城的繁华与衰落。灞桥作为送别之桥，承载着中国人深厚的情感寄托。",
      "mainDynasty": "汉",
      "mainType": "拱桥",
      "climate": "温带季风气候，四季分明"
    },
    "安徽": {
      "name": "安徽",
      "title": "徽州桥韵",
      "subtitle": "徽商故里的桥梁艺术",
      "count": 4,
      "history": "安徽地处华东腹地，徽州文化源远流长。徽商的崛起带动了桥梁建造的繁荣，许多古桥至今保存完好。徽州古桥以石拱桥为主，造型典雅，与徽派建筑相得益彰。",
      "features": [
        "徽派建筑风格独特",
        "石拱桥工艺精湛",
        "桥梁与村落融为一体",
        "徽商文化影响深远"
      ],
      "representatives": [
        {
          "name": "太平桥",
          "dynasty": "明",
          "span": "268米",
          "description": "徽州地区最大的古石拱桥，横跨练江"
        },
        {
          "name": "许村高阳桥",
          "dynasty": "元",
          "span": "42米",
          "description": "徽州廊桥代表作，桥上建廊，造型精美"
        }
      ],
      "stories": [
        {
          "title": "太平桥的建造",
          "content": "太平桥由明代徽商捐资建造，是徽商回馈乡里的典范。桥为十六孔石拱桥，横跨练江，气势恢宏。桥上石雕精美，展现了徽州工匠的高超技艺。"
        }
      ],
      "culture": "安徽古桥是徽州文化的重要组成部分，见证了徽商的辉煌历史。桥梁上的石雕、木雕精美绝伦，反映了徽州人民的审美情趣和工艺水平。",
      "mainDynasty": "明",
      "mainType": "拱桥",
      "climate": "亚热带季风气候，四季分明"
    },
    "山东": {
      "name": "山东",
      "title": "齐鲁桥韵",
      "subtitle": "孔孟之乡的桥梁遗存",
      "count": 3,
      "history": "山东是孔孟之乡，儒家文化的发祥地。泰山、黄河孕育了独特的齐鲁文化。山东古桥以石拱桥为主，结构坚固，造型古朴，体现了北方桥梁的典型特征。",
      "features": [
        "石拱桥结构坚固",
        "儒家文化影响深远",
        "桥梁造型古朴大方",
        "黄河文化特色鲜明"
      ],
      "representatives": [
        {
          "name": "泗水桥",
          "dynasty": "明",
          "span": "150米",
          "description": "山东著名古桥，横跨泗水河"
        }
      ],
      "stories": [
        {
          "title": "泗水桥的传说",
          "content": "泗水是孔子讲学之地，泗水桥因此承载着深厚的文化内涵。相传孔子曾在此桥上驻足，感叹时光流逝。后人建桥纪念，故名泗水桥。"
        }
      ],
      "culture": "山东古桥承载着儒家文化的精神内涵，见证了齐鲁大地的历史变迁。桥梁上的碑刻、题记记录了历代文人的吟咏，是珍贵的文化遗产。",
      "mainDynasty": "明",
      "mainType": "拱桥",
      "climate": "温带季风气候，四季分明"
    },
    "湖北": {
      "name": "湖北",
      "title": "荆楚桥韵",
      "subtitle": "长江中游的桥梁明珠",
      "count": 3,
      "history": "湖北地处长江中游，荆楚文化源远流长。长江、汉江纵横全境，桥梁建造历史悠久。湖北古桥以石拱桥为主，融合了南北桥梁风格，形成了独特的荆楚特色。",
      "features": [
        "长江中游桥梁众多",
        "荆楚文化影响深远",
        "南北桥梁风格融合",
        "历史文化底蕴深厚"
      ],
      "representatives": [
        {
          "name": "晴川桥",
          "dynasty": "清",
          "span": "200米",
          "description": "武汉三镇古桥代表，横跨汉江"
        }
      ],
      "stories": [
        {
          "title": "晴川桥与黄鹤楼",
          "content": "晴川桥与黄鹤楼隔江相望，是武汉三镇的标志性建筑。古人登黄鹤楼，望晴川桥，留下无数诗词佳作。'晴川历历汉阳树，芳草萋萋鹦鹉洲'便是其中的名句。"
        }
      ],
      "culture": "湖北古桥是荆楚文化的重要组成部分，见证了长江中游的历史变迁。桥梁与黄鹤楼、晴川阁等名胜相映成趣，构成了独特的江城景观。",
      "mainDynasty": "清",
      "mainType": "拱桥",
      "climate": "亚热带季风气候，四季分明"
    },
    "河南": {
      "name": "河南",
      "title": "中原桥韵",
      "subtitle": "华夏文明的桥梁遗存",
      "count": 2,
      "history": "河南地处中原，是华夏文明的发祥地。黄河横贯全境，桥梁建造历史悠久。小商桥作为隋代石拱桥的代表作，是中国桥梁史上的珍贵遗产。河南古桥见证了中原大地的历史变迁。",
      "features": [
        "历史悠久的石拱桥",
        "中原文化底蕴深厚",
        "黄河文化影响深远",
        "古桥遗存珍贵"
      ],
      "representatives": [
        {
          "name": "小商桥",
          "dynasty": "隋",
          "span": "21.3米",
          "description": "世界现存最早的敞肩石拱桥之一，比赵州桥更早"
        }
      ],
      "stories": [
        {
          "title": "小商桥的发现",
          "content": "小商桥长期被埋没于历史尘埃中，直到近代才被重新发现。经考证，此桥建于隋代，比著名的赵州桥还要早，是世界桥梁史上的珍贵遗产。"
        }
      ],
      "culture": "河南古桥是中原文化的载体，见证了华夏文明的起源与发展。小商桥作为世界最早的敞肩石拱桥之一，是中国古代桥梁技术的杰出代表。",
      "mainDynasty": "隋",
      "mainType": "拱桥",
      "climate": "温带季风气候，四季分明"
    },
    "辽宁": {
      "name": "辽宁",
      "title": "辽东桥韵",
      "subtitle": "东北地区的桥梁遗存",
      "count": 1,
      "history": "辽宁地处东北，是满族的发祥地。辽河纵贯全境，桥梁建造历史悠久。辽宁古桥以石拱桥为主，融合了满族文化特色，形成了独特的东北风格。",
      "features": [
        "东北风格独特",
        "满族文化影响",
        "石拱桥结构坚固",
        "历史遗存珍贵"
      ],
      "representatives": [
        {
          "name": "辽东古桥",
          "dynasty": "清",
          "span": "50米",
          "description": "东北地区保存完好的清代石拱桥"
        }
      ],
      "stories": [
        {
          "title": "辽东古桥的故事",
          "content": "辽东古桥建于清代，是东北地区保存最完好的古桥之一。桥身用青石砌成，结构坚固，历经数百年风雨依然屹立。"
        }
      ],
      "culture": "辽宁古桥是东北文化的重要组成部分，见证了满族的历史变迁。桥梁上的雕刻反映了满族的审美情趣和文化传统。",
      "mainDynasty": "清",
      "mainType": "拱桥",
      "climate": "温带季风气候，冬季寒冷"
    },
    "甘肃": {
      "name": "甘肃",
      "title": "陇右桥韵",
      "subtitle": "丝绸之路的桥梁遗存",
      "count": 1,
      "history": "甘肃地处西北，是丝绸之路的重要通道。黄河穿流而过，桥梁建造历史悠久。甘肃古桥以索桥、浮桥为主，适应了西北地区河流湍急的特点。",
      "features": [
        "丝绸之路文化影响",
        "索桥技术独特",
        "西北风格鲜明",
        "历史价值突出"
      ],
      "representatives": [
        {
          "name": "河西古桥",
          "dynasty": "明",
          "span": "80米",
          "description": "河西走廊保存完好的明代古桥"
        }
      ],
      "stories": [
        {
          "title": "河西古桥与丝路",
          "content": "河西古桥位于丝绸之路要道上，见证了东西方文化的交流。商旅往来，驼铃声声，这座古桥承载着千年的历史记忆。"
        }
      ],
      "culture": "甘肃古桥是丝路文化的重要组成部分，见证了东西方文明的交流与融合。桥梁上的遗迹记录了丝绸之路的繁华历史。",
      "mainDynasty": "明",
      "mainType": "拱桥",
      "climate": "温带大陆性气候，干燥少雨"
    }
  },
  "dynasties": {
    "汉": {
      "name": "汉",
      "period": "公元前206年-公元220年",
      "description": "汉代是中国古代桥梁发展的重要时期。随着丝绸之路的开通，桥梁建造技术得到推广。汉代桥梁以木梁桥和浮桥为主，石拱桥开始出现。",
      "features": [
        "木梁桥技术成熟",
        "浮桥应用广泛",
        "石拱桥开始出现"
      ],
      "representatives": [
        "灞桥",
        "渭桥"
      ]
    },
    "三国": {
      "name": "三国",
      "period": "公元220-280年",
      "description": "三国时期战乱频繁，桥梁建造以军事用途为主。栈道桥和索桥在西南地区得到发展。",
      "features": [
        "军事桥梁发展",
        "栈道桥技术进步",
        "索桥在西南地区应用"
      ],
      "representatives": [
        "剑阁栈道"
      ]
    },
    "晋": {
      "name": "晋",
      "period": "公元265-420年",
      "description": "两晋时期，桥梁建造技术继续发展。石拱桥技术逐渐成熟，南方水乡地区桥梁数量增加。",
      "features": [
        "石拱桥技术成熟",
        "南方桥梁增多",
        "园林桥梁出现"
      ],
      "representatives": [
        "洛阳桥前身"
      ]
    },
    "南北朝": {
      "name": "南北朝",
      "period": "公元420-589年",
      "description": "南北朝时期，佛教兴盛，寺庙桥梁大量建造。石拱桥技术进一步发展，为隋唐桥梁的辉煌奠定基础。",
      "features": [
        "寺庙桥梁增多",
        "石拱桥技术发展",
        "桥梁装饰艺术兴起"
      ],
      "representatives": [
        "赵州桥前身"
      ]
    },
    "隋": {
      "name": "隋",
      "period": "公元581-618年",
      "description": "隋代是中国古代桥梁发展的巅峰时期。赵州桥的建造开创了敞肩拱桥的先河，技术领先世界近千年。大运河的开通也催生了大量桥梁的建造。",
      "features": [
        "敞肩拱技术世界首创",
        "大运河桥梁大量建造",
        "工程技术达到巅峰"
      ],
      "representatives": [
        "赵州桥"
      ]
    },
    "唐": {
      "name": "唐",
      "period": "公元618-907年",
      "description": "唐代国力强盛，桥梁建造进入繁荣期。长安、洛阳等大都市桥梁众多，石拱桥技术成熟。唐代诗人留下了大量咏桥诗篇，桥梁文化丰富多彩。",
      "features": [
        "桥梁数量大增",
        "石拱桥技术成熟",
        "桥梁文化繁荣"
      ],
      "representatives": [
        "宝带桥",
        "枫桥"
      ]
    },
    "五代": {
      "name": "五代",
      "period": "公元907-960年",
      "description": "五代十国时期，南方政权相对稳定，桥梁建造继续发展。吴越国在浙江地区建造了大量桥梁。",
      "features": [
        "南方桥梁发展",
        "吴越桥梁建造",
        "技术传承延续"
      ],
      "representatives": [
        "杭州古桥"
      ]
    },
    "宋": {
      "name": "宋",
      "period": "公元960-1279年",
      "description": "宋代是中国古代桥梁发展的黄金时期。经济繁荣、技术进步，桥梁建造达到前所未有的高度。洛阳桥、安平桥等跨海石梁桥的建造，代表了中国桥梁技术的最高成就。",
      "features": [
        "跨海石梁桥技术领先",
        "桥梁数量达到高峰",
        "工程技术全面发展"
      ],
      "representatives": [
        "洛阳桥",
        "安平桥",
        "八字桥"
      ]
    },
    "元": {
      "name": "元",
      "period": "公元1271-1368年",
      "description": "元代疆域辽阔，交通发达，桥梁建造延续了宋代的繁荣。卢沟桥的建造体现了元代桥梁技术的高超水平。",
      "features": [
        "交通网络完善",
        "桥梁技术传承",
        "大型桥梁建造"
      ],
      "representatives": [
        "卢沟桥"
      ]
    },
    "明": {
      "name": "明",
      "period": "公元1368-1644年",
      "description": "明代国力强盛，桥梁建造进入又一个高峰期。广济桥、永济桥等大型桥梁的建造，代表了明代桥梁技术的最高成就。廊桥、风雨桥等特色桥梁大量出现。",
      "features": [
        "大型桥梁建造",
        "廊桥技术发展",
        "桥梁装饰精美"
      ],
      "representatives": [
        "广济桥",
        "永济桥"
      ]
    },
    "清": {
      "name": "清",
      "period": "公元1644-1912年",
      "description": "清代是中国古代桥梁发展的最后一个高峰期。皇家园林桥梁建造达到极高水平，少数民族地区的风雨桥、铁索桥也得到发展。泸定桥、十七孔桥等桥梁成为经典之作。",
      "features": [
        "皇家园林桥梁精美",
        "少数民族桥梁发展",
        "铁索桥技术成熟"
      ],
      "representatives": [
        "泸定桥",
        "十七孔桥",
        "双龙桥"
      ]
    },
    "近代": {
      "name": "近代",
      "period": "公元1912-1949年",
      "description": "近代以来，传统桥梁建造技术逐渐被现代技术取代，但仍有一些传统桥梁得到保护和修缮。古桥作为文化遗产，受到越来越多的重视。",
      "features": [
        "传统技术传承",
        "古桥保护修缮",
        "文化遗产保护"
      ],
      "representatives": [
        "钱塘江大桥"
      ]
    }
  }
}